cupy/__init__.py
cupy/_environment.py
cupy/_util.cpython-37m-x86_64-linux-gnu.so
cupy/_version.py
cupy/cublas.py
cupy/cudnn.cpython-37m-x86_64-linux-gnu.so
cupy/cusolver.cpython-37m-x86_64-linux-gnu.so
cupy/cusparse.py
cupy/.data/_wheel.json
cupy/_binary/__init__.py
cupy/_binary/elementwise.py
cupy/_binary/packing.py
cupy/_core/__init__.py
cupy/_core/_accelerator.cpython-37m-x86_64-linux-gnu.so
cupy/_core/_carray.cpython-37m-x86_64-linux-gnu.so
cupy/_core/_codeblock.py
cupy/_core/_cub_reduction.cpython-37m-x86_64-linux-gnu.so
cupy/_core/_dtype.cpython-37m-x86_64-linux-gnu.so
cupy/_core/_fusion_interface.py
cupy/_core/_fusion_kernel.cpython-37m-x86_64-linux-gnu.so
cupy/_core/_fusion_op.py
cupy/_core/_fusion_optimization.py
cupy/_core/_fusion_thread_local.cpython-37m-x86_64-linux-gnu.so
cupy/_core/_fusion_trace.cpython-37m-x86_64-linux-gnu.so
cupy/_core/_fusion_variable.cpython-37m-x86_64-linux-gnu.so
cupy/_core/_gufuncs.py
cupy/_core/_kernel.cpython-37m-x86_64-linux-gnu.so
cupy/_core/_memory_range.cpython-37m-x86_64-linux-gnu.so
cupy/_core/_optimize_config.cpython-37m-x86_64-linux-gnu.so
cupy/_core/_reduction.cpython-37m-x86_64-linux-gnu.so
cupy/_core/_routines_binary.cpython-37m-x86_64-linux-gnu.so
cupy/_core/_routines_indexing.cpython-37m-x86_64-linux-gnu.so
cupy/_core/_routines_linalg.cpython-37m-x86_64-linux-gnu.so
cupy/_core/_routines_logic.cpython-37m-x86_64-linux-gnu.so
cupy/_core/_routines_manipulation.cpython-37m-x86_64-linux-gnu.so
cupy/_core/_routines_math.cpython-37m-x86_64-linux-gnu.so
cupy/_core/_routines_sorting.cpython-37m-x86_64-linux-gnu.so
cupy/_core/_routines_statistics.cpython-37m-x86_64-linux-gnu.so
cupy/_core/_scalar.cpython-37m-x86_64-linux-gnu.so
cupy/_core/_ufuncs.py
cupy/_core/core.cpython-37m-x86_64-linux-gnu.so
cupy/_core/dlpack.cpython-37m-x86_64-linux-gnu.so
cupy/_core/flags.cpython-37m-x86_64-linux-gnu.so
cupy/_core/fusion.cpython-37m-x86_64-linux-gnu.so
cupy/_core/internal.cpython-37m-x86_64-linux-gnu.so
cupy_cuda92-9.6.0.dist-info/METADATA
cupy_cuda92-9.6.0.dist-info/WHEEL
cupy_cuda92-9.6.0.dist-info/license.rst
cupy_cuda92-9.6.0.dist-info/top_level.txt
cupy_cuda92-9.6.0.dist-info/RECORD
