Metadata-Version: 2.1
Name: cupy-cuda92
Version: 9.6.0
Summary: CuPy: NumPy & SciPy for GPU
Home-page: https://cupy.dev/
Author: Seiya Tokui
Author-email: tokui@preferred.jp
Maintainer: CuPy Developers
License: MIT License
Project-URL: Bug Tracker, https://github.com/cupy/cupy/issues
Project-URL: Documentation, https://docs.cupy.dev/
Project-URL: Source Code, https://github.com/cupy/cupy
Platform: UNKNOWN
Classifier: Development Status :: 5 - Production/Stable
Classifier: Intended Audience :: Science/Research
Classifier: Intended Audience :: Developers
Classifier: License :: OSI Approved :: MIT License
Classifier: Programming Language :: Python
Classifier: Programming Language :: Python :: 3
Classifier: Programming Language :: Python :: 3.6
Classifier: Programming Language :: Python :: 3.7
Classifier: Programming Language :: Python :: 3.8
Classifier: Programming Language :: Python :: 3.9
Classifier: Programming Language :: Python :: 3 :: Only
Classifier: Programming Language :: Cython
Classifier: Topic :: Software Development
Classifier: Topic :: Scientific/Engineering
Classifier: Operating System :: POSIX
Classifier: Operating System :: Microsoft :: Windows
Requires-Python: >=3.6.0
License-File: docs/source/license.rst
Requires-Dist: numpy (<1.24,>=1.17)
Requires-Dist: fastrlock (>=0.5)
Provides-Extra: all
Requires-Dist: scipy (<1.10,>=1.4) ; extra == 'all'
Requires-Dist: Cython (<3,>=0.29.22) ; extra == 'all'
Requires-Dist: optuna (>=2.0) ; extra == 'all'
Provides-Extra: jenkins
Requires-Dist: pytest (>=6.2) ; extra == 'jenkins'
Requires-Dist: pytest-timeout ; extra == 'jenkins'
Requires-Dist: pytest-cov ; extra == 'jenkins'
Requires-Dist: coveralls ; extra == 'jenkins'
Requires-Dist: codecov ; extra == 'jenkins'
Requires-Dist: coverage (<5) ; extra == 'jenkins'
Provides-Extra: setup
Requires-Dist: Cython (<3,>=0.29.22) ; extra == 'setup'
Requires-Dist: fastrlock (>=0.5) ; extra == 'setup'
Provides-Extra: stylecheck
Requires-Dist: autopep8 (==1.5.5) ; extra == 'stylecheck'
Requires-Dist: flake8 (==3.8.4) ; extra == 'stylecheck'
Requires-Dist: pbr (==5.5.1) ; extra == 'stylecheck'
Requires-Dist: pycodestyle (==2.6.0) ; extra == 'stylecheck'
Provides-Extra: test
Requires-Dist: pytest (>=6.2) ; extra == 'test'
